tiendanube
