Metadata-Version: 1.0
Name: tiendanube
Version: 1.1
Summary: UNKNOWN
Home-page: https://github.com/catalanojuan/tiendanube-python
Author: Juan Catalano
Author-email: catalanojuan@gmail.com
License: MIT
Download-URL: https://github.com/catalanojuan/tiendanube-python/tarball/1.1
Platform: UNKNOWN
Classifier: Development Status :: 4 - Beta
Classifier: Environment :: Web Environment
Classifier: Intended Audience :: Developers
Classifier: License :: OSI Approved :: MIT License
Classifier: Natural Language :: English
Classifier: Programming Language :: Python
Classifier: Programming Language :: Python :: 2.7
